setup.py
css_py/__init__.py
css_py/css_py.py
css_py.egg-info/PKG-INFO
css_py.egg-info/SOURCES.txt
css_py.egg-info/dependency_links.txt
css_py.egg-info/not-zip-safe
css_py.egg-info/top_level.txt