Metadata-Version: 1.0
Name: css-py
Version: 0.1
Summary: CSS python
Home-page: UNKNOWN
Author: UNKNOWN
Author-email: myemail@something.com
License: UNKNOWN
Platform: UNKNOWN
